harish_ai_assistant/__init__.py
harish_ai_assistant/assistant.py
harish_ai_assistant/cli.py
harish_ai_assistant/agents/__init__.py
harish_ai_assistant/agents/router.py
harish_ai_assistant/config/__init__.py
harish_ai_assistant/core/__init__.py
harish_ai_assistant/core/cli.py
harish_ai_assistant/core/graph.py
harish_ai_assistant/core/models.py
harish_ai_assistant/core/state.py
harish_ai_assist-0.1.1.dist-info/METADATA
harish_ai_assist-0.1.1.dist-info/WHEEL
harish_ai_assist-0.1.1.dist-info/entry_points.txt
harish_ai_assist-0.1.1.dist-info/top_level.txt
harish_ai_assist-0.1.1.dist-info/RECORD
