Metadata-Version: 2.4
Name: harish-ai-assist
Version: 0.1.1
Summary: Interactive AI code generator with CLI
Requires-Python: >=3.10
Requires-Dist: openai
Requires-Dist: opencv-python
Requires-Dist: matplotlib
Requires-Dist: numpy
Requires-Dist: langchain
Requires-Dist: langgraph
